Analysis/UnsupervisedBinning.py
Analysis/__init__.py
UnsupervisedBinning-0.1.0.dist-info/METADATA
UnsupervisedBinning-0.1.0.dist-info/WHEEL
UnsupervisedBinning-0.1.0.dist-info/top_level.txt
UnsupervisedBinning-0.1.0.dist-info/RECORD
